{
    "Logging": {
        "LogLevel": {
            "Default": "Debug",
            "System": "Information",
            "Microsoft": "Information"
        }
    },
    "Exception": {
        "UnSupportedOS": "Belirtilen platform veya işletim sistemi için API'nin desteklenmediğini gösterir. Bir sürüm belirtilmişse, API önceki bir sürümden çağrılamaz.",
        "OperatingNull": "Null yapılabilir türden bir değişkeni, temel alınan türe çevirmeden önce, değerin boş olmadığından emin olmalısınız.",
        "InnerException": "OpenQA.Selenium.WebDriverException: The HTTP request to the remote WebDriver server for URL",
        "ExceptionInnerMessage": "HTTP request to the remote WebDriver server for URL",
        "ExpectedExceptionMessage": "Unable to connect to the remote server"
    },
    "Uri": {
        "BaseUrl": "https://test.motivist.com",
        "Admin/Missions/COM": "/Admin/Missions/COM"
    },
    "Context": {
        "username": "furkan.aydin",
        "password": "Hadate25.",
        "captcha": "NOOSN"
    }
}